LICENSE.txt
MANIFEST.in
README.rst
Tool.py
setup.py
hytestlib/__init__.py
hytestlib/hylibone.py
hytestlib.egg-info/PKG-INFO
hytestlib.egg-info/SOURCES.txt
hytestlib.egg-info/dependency_links.txt
hytestlib.egg-info/top_level.txt