Metadata-Version: 1.0
Name: hytestlib
Version: 1.0.2
Summary: this is a great lib,too
Home-page: https://github.com/hy/Python_code
Author: Hy
Author-email: 843923647@qq.com
License: MIT
Platform: UNKNOWN
